pytask_r/__init__.py
pytask_r/_version.py
pytask_r/collect.py
pytask_r/config.py
pytask_r/execute.py
pytask_r/plugin.py
pytask_r/py.typed
pytask_r/serialization.py
pytask_r/shared.py
pytask_r-0.4.1.dist-info/METADATA
pytask_r-0.4.1.dist-info/WHEEL
pytask_r-0.4.1.dist-info/entry_points.txt
pytask_r-0.4.1.dist-info/licenses/LICENSE
pytask_r-0.4.1.dist-info/RECORD
