Metadata-Version: 2.3
Name: pytask_r
Version: 0.4.1
Summary: Run R scripts with pytask.
Project-URL: Homepage, https://github.com/pytask-dev/pytask-r
Project-URL: Changelog, https://github.com/pytask-dev/pytask-r/blob/main/CHANGES.md
Project-URL: Documentation, https://github.com/pytask-dev/pytask-r
Project-URL: Github, https://github.com/pytask-dev/pytask-r
Project-URL: Tracker, https://github.com/pytask-dev/pytask-r/issues
Author-email: Tobias Raabe <raabe@posteo.de>
License: MIT
License-File: LICENSE
Classifier: Development Status :: 4 - Beta
Classifier: License :: OSI Approved :: MIT License
Classifier: Operating System :: OS Independent
Classifier: Programming Language :: Python :: 3
Classifier: Programming Language :: Python :: 3 :: Only
Classifier: Programming Language :: R
Requires-Python: >=3.8
Requires-Dist: click
Requires-Dist: pluggy>=1.0.0
Requires-Dist: pytask>=0.4.5
Provides-Extra: test
Requires-Dist: pytask-parallel; extra == 'test'
Requires-Dist: pytest; extra == 'test'
Requires-Dist: pytest-cov; extra == 'test'
Requires-Dist: pytest-xdist; extra == 'test'
Requires-Dist: pyyaml; extra == 'test'
